setup.py
jsoncompare/__init__.py
jsoncompare/jsoncompare.py
jsoncompare.egg-info/PKG-INFO
jsoncompare.egg-info/SOURCES.txt
jsoncompare.egg-info/dependency_links.txt
jsoncompare.egg-info/top_level.txt
jsoncompare/test/__init__.py
jsoncompare/test/jsondiffstack.py
jsoncompare/test/test_jsoncompare.py