Metadata-Version: 1.0
Name: jsoncompare
Version: 0.1.2
Summary: Json comparison tool
Home-page: https://github.com/dandroid88/jsoncompare
Author: Daniel Myers
Author-email: dmandroid88@gmail.com
License: UNKNOWN
Keywords: json comparison compare order
Platform: UNKNOWN
